cesglab/__init__.py
cesglab/__main__.py
cesglab/main.py
cesglab-0.1.1.dist-info/LICENSE
cesglab-0.1.1.dist-info/METADATA
cesglab-0.1.1.dist-info/WHEEL
cesglab-0.1.1.dist-info/entry_points.txt
cesglab-0.1.1.dist-info/top_level.txt
cesglab-0.1.1.dist-info/RECORD
